dceapi/__init__.py
dceapi/client.py
dceapi/config.py
dceapi/errors.py
dceapi/http.py
dceapi/models.py
dceapi/token.py
dceapi/services/__init__.py
dceapi/services/common.py
dceapi/services/delivery.py
dceapi/services/market.py
dceapi/services/member.py
dceapi/services/news.py
dceapi/services/settle.py
dceapi/services/trade.py
dceapi-0.1.2.dist-info/METADATA
dceapi-0.1.2.dist-info/WHEEL
dceapi-0.1.2.dist-info/top_level.txt
dceapi-0.1.2.dist-info/RECORD
