Metadata-Version: 2.4
Name: dceapi
Version: 0.1.2
Summary: 大连商品交易所 (DCE) API v1.0 Python SDK
Author-email: pseudocodes <pseudocodes@gmail.com>
Project-URL: Homepage, https://github.com/pseudocodes/dceapi-py
Project-URL: Repository, https://github.com/pseudocodes/dceapi-py
Keywords: dce,futures,commodities,trading,api
Classifier: Development Status :: 4 - Beta
Classifier: Intended Audience :: Developers
Classifier: License :: OSI Approved :: MIT License
Classifier: Programming Language :: Python :: 3
Classifier: Programming Language :: Python :: 3.8
Classifier: Programming Language :: Python :: 3.9
Classifier: Programming Language :: Python :: 3.10
Classifier: Programming Language :: Python :: 3.11
Classifier: Programming Language :: Python :: 3.12
Requires-Python: >=3.8
Requires-Dist: requests>=2.31.0
Requires-Dist: typing-extensions>=4.8.0; python_version < "3.10"
Provides-Extra: dev
Requires-Dist: pytest>=7.4.0; extra == "dev"
Requires-Dist: pytest-cov>=4.1.0; extra == "dev"
Requires-Dist: black>=23.0.0; extra == "dev"
Requires-Dist: mypy>=1.5.0; extra == "dev"
Requires-Dist: ruff>=0.0.290; extra == "dev"
